CMakeLists.txt
MANIFEST.in
README.md
pyproject.toml
setup.py
samples/haxpy.py
samples/override_parameters.py
samples/saxpy.py
samples/saxpybatched.py
samples/sgemm.py
samples/sgemv.py
src/pyclblast.pyx
src/pyclblast.egg-info/PKG-INFO
src/pyclblast.egg-info/SOURCES.txt
src/pyclblast.egg-info/dependency_links.txt
src/pyclblast.egg-info/requires.txt
src/pyclblast.egg-info/top_level.txt
test/test_pyclblast.py