Metadata-Version: 2.1
Name: pyclblast
Version: 1.4.0
Summary: Python bindings for CLBlast, the tuned OpenCL BLAS library
Author-email: Cedric Nugteren <web@cedricnugteren.nl>
License: Apache Software License
Project-URL: Homepage, https://github.com/CNugteren/CLBlast/blob/master/src/pyclblast
Keywords: OpenCL,BLAS,CLBlast,GEMM,matrix-multiplication
Classifier: Development Status :: 4 - Beta
Classifier: Intended Audience :: Developers
Classifier: Topic :: Software Development :: Libraries
Classifier: License :: OSI Approved :: Apache Software License
Classifier: Programming Language :: Python :: 2
Classifier: Programming Language :: Python :: 3
